stepup/reprep/__init__.py
stepup/reprep/actions.py
stepup/reprep/add_notes_pdf.py
stepup/reprep/api.py
stepup/reprep/bibparser.py
stepup/reprep/bibsane.py
stepup/reprep/bibtex.lark
stepup/reprep/bibtex_log.py
stepup/reprep/cat_pdf.py
stepup/reprep/check_hrefs.py
stepup/reprep/check_inventory.py
stepup/reprep/compile_latex.py
stepup/reprep/compile_tectonic.py
stepup/reprep/compile_typst.py
stepup/reprep/convert_inkscape.py
stepup/reprep/convert_markdown.py
stepup/reprep/convert_weasyprint.py
stepup/reprep/execute_papermill.py
stepup/reprep/flatten_latex.py
stepup/reprep/inventory.py
stepup/reprep/latex_deps.py
stepup/reprep/latex_log.py
stepup/reprep/make_inventory.py
stepup/reprep/normalize_pdf.py
stepup/reprep/nup_pdf.py
stepup/reprep/pytest.py
stepup/reprep/raster_pdf.py
stepup/reprep/sync_zenodo.py
stepup/reprep/tile_pdf.py
stepup/reprep/unplot.py
stepup/reprep/wrap_git.py
stepup/reprep/zip_inventory.py
stepup_reprep-3.1.8.dist-info/licenses/LICENSE
stepup_reprep-3.1.8.dist-info/METADATA
stepup_reprep-3.1.8.dist-info/WHEEL
stepup_reprep-3.1.8.dist-info/entry_points.txt
stepup_reprep-3.1.8.dist-info/top_level.txt
stepup_reprep-3.1.8.dist-info/RECORD
