Metadata-Version: 2.4
Name: stepup-reprep
Version: 3.1.8
Summary: StepUp RepRep is the StepUp extension for Reproducible Reporting
Author-email: Toon Verstraelen <toon.verstraelen@ugent.be>
License-Expression: GPL-3.0-or-later
Project-URL: Documentation, https://reproducible-reporting.github.io/stepup-reprep/
Project-URL: Issues, https://github.com/reproducible-reporting/stepup-reprep/issues
Project-URL: Source, https://github.com/reproducible-reporting/stepup-reprep/
Project-URL: Changelog, https://reproducible-reporting.github.io/stepup-reprep/changelog/
Classifier: Development Status :: 4 - Beta
Classifier: Environment :: Console
Classifier: Intended Audience :: Education
Classifier: Intended Audience :: Science/Research
Classifier: Natural Language :: English
Classifier: Operating System :: POSIX
Classifier: Operating System :: MacOS
Classifier: Programming Language :: Python :: 3
Classifier: Programming Language :: Python :: 3.11
Classifier: Programming Language :: Python :: 3.12
Classifier: Programming Language :: Python :: 3.13
Classifier: Programming Language :: Python :: 3.14
Classifier: Topic :: Scientific/Engineering
Classifier: Topic :: Education :: Computer Aided Instruction (CAI)
Classifier: Topic :: Text Processing
Classifier: Topic :: Text Processing :: Markup :: LaTeX
Classifier: Topic :: Text Processing :: Markup :: Markdown
Requires-Python: >=3.11
License-File: LICENSE
Requires-Dist: attrs>=23.1.0
Requires-Dist: cattrs>=23.1.2
Requires-Dist: defusedxml>=0.7.0
Requires-Dist: idutils>=1.4.5
Requires-Dist: ipykernel>=6.20.1
Requires-Dist: lark>=1.3.1
Requires-Dist: markdown-it-py>=3.0.0
Requires-Dist: mdit-py-plugins>=0.4.2
Requires-Dist: nbconvert>=7.1.0
Requires-Dist: numpy>=1.24.3
Requires-Dist: papermill>=2.6.0
Requires-Dist: path>=16.14.0
Requires-Dist: pyiso4>=0.1.6
Requires-Dist: pymupdf>=1.23.7
Requires-Dist: pyyaml>=6.0
Requires-Dist: requests>=2.32.4
Requires-Dist: scipy>=1.11.1
Requires-Dist: semver>=3.0.0
Requires-Dist: stepup<4.0.0,>=3.2.0
Requires-Dist: svg.path>=6.0
Requires-Dist: weasyprint>=63.1
Provides-Extra: dev
Requires-Dist: psutil; extra == "dev"
Requires-Dist: pytest; extra == "dev"
Requires-Dist: pytest-asyncio>=0.24; extra == "dev"
Requires-Dist: pytest-xdist; extra == "dev"
Requires-Dist: matplotlib; extra == "dev"
Requires-Dist: mike; extra == "dev"
Requires-Dist: mkdocs; extra == "dev"
Requires-Dist: mkdocstrings[python]; extra == "dev"
Requires-Dist: mkdocs-macros-plugin; extra == "dev"
Requires-Dist: mkdocs-material; extra == "dev"
Dynamic: license-file
